README.md
setup.cfg
setup.py
easyds/__init__.py
easyds/data_cleaner.py
easyds/text_cleaner.py
easyds.egg-info/PKG-INFO
easyds.egg-info/SOURCES.txt
easyds.egg-info/dependency_links.txt
easyds.egg-info/requires.txt
easyds.egg-info/top_level.txt
tests/__init__.py
tests/test_data_cleaner.py
tests/test_text_cleaner.py