Metadata-Version: 2.1
Name: easyds
Version: 0.1.1
Summary: Personal Python library to make usual data science workflow easy.
Home-page: https://github.com/king-ds/easyds
Author: Ricardo Calura
Author-email: ricardo.calura29@gmail.com
License: MIT License
Platform: UNKNOWN
